pelican_github_activity/__init__.py
pelican_github_activity/github_activity.py
pelican_github_activity-0.1.0.dist-info/LICENSE
pelican_github_activity-0.1.0.dist-info/METADATA
pelican_github_activity-0.1.0.dist-info/WHEEL
pelican_github_activity-0.1.0.dist-info/top_level.txt
pelican_github_activity-0.1.0.dist-info/RECORD
