Metadata-Version: 2.1
Name: pelican-github-activity
Version: 0.1.0
Summary: Pelican github activity modified to work with nice-blog theme
Home-page: http://github.com/JWKennington/pelican-github-activity
Author: James W. Kennington
Author-email: jameswkennington@gmail.com
License: MIT
Platform: UNKNOWN
